markdown_hashtag/__init__.py
markdown_hashtag/hashtag.py
markdown_hashtag-0.1.1.dist-info/licenses/LICENSE
markdown_hashtag-0.1.1.dist-info/METADATA
markdown_hashtag-0.1.1.dist-info/WHEEL
markdown_hashtag-0.1.1.dist-info/entry_points.txt
markdown_hashtag-0.1.1.dist-info/top_level.txt
markdown_hashtag-0.1.1.dist-info/RECORD
