Metadata-Version: 2.4
Name: markdown-hashtag
Version: 0.1.1
Summary: Extension for Python-Markdown to parse hashtag (e.g. #Python) into a user-defined URL
Home-page: https://github.com/becksta-dev/markdown-hashtag
Author: Vinzenz Becke-Stauner (Becksta)
Author-email: info@becke-stauner.de
License: GPLv3
Classifier: Programming Language :: Python :: 3
Classifier: License :: OSI Approved :: GNU General Public License v3 (GPLv3)
Requires-Python: >=3.6
License-File: LICENSE
Requires-Dist: markdown>=3.0
Dynamic: author
Dynamic: author-email
Dynamic: classifier
Dynamic: description
Dynamic: description-content-type
Dynamic: home-page
Dynamic: license
Dynamic: license-file
Dynamic: requires-dist
Dynamic: requires-python
Dynamic: summary
